msgbuzz/__init__.py
msgbuzz/generic.py
msgbuzz/rabbitmq.py
msgbuzz-0.1.3.dist-info/LICENSE
msgbuzz-0.1.3.dist-info/METADATA
msgbuzz-0.1.3.dist-info/WHEEL
msgbuzz-0.1.3.dist-info/top_level.txt
msgbuzz-0.1.3.dist-info/RECORD
